{
  "sections": {
    "main": {
      "type": "main-page",
      "settings": {
        "padding_top": 28,
        "padding_bottom": 28
      }
    },
    "40304770-665c-4079-ab03-58ad2ee6edae": {
      "type": "te-image-banner",
      "blocks": {
        "template--16679765836021__40304770-665c-4079-ab03-58ad2ee6edae-1679500848d4518458-1": {
          "type": "title",
          "settings": {
            "banner__title": "<p><em><strong>Developmentally<\/strong><\/em> mindful play<\/p>"
          }
        },
        "template--16679765836021__40304770-665c-4079-ab03-58ad2ee6edae-1679500848d4518458-0": {
          "type": "caption",
          "settings": {
            "banner__caption": "Montessori-inspired toys for growing minds"
          }
        },
        "template--16679765836021__40304770-665c-4079-ab03-58ad2ee6edae-1679500848d4518458-2": {
          "type": "subtitle",
          "settings": {
            "banner__subtitle": ""
          }
        },
        "template--16679765836021__40304770-665c-4079-ab03-58ad2ee6edae-1679500848d4518458-3": {
          "type": "image",
          "settings": {
            "banner__image": "shopify:\/\/shop_images\/loft-donna.jpg"
          }
        }
      },
      "block_order": [
        "template--16679765836021__40304770-665c-4079-ab03-58ad2ee6edae-1679500848d4518458-1",
        "template--16679765836021__40304770-665c-4079-ab03-58ad2ee6edae-1679500848d4518458-0",
        "template--16679765836021__40304770-665c-4079-ab03-58ad2ee6edae-1679500848d4518458-2",
        "template--16679765836021__40304770-665c-4079-ab03-58ad2ee6edae-1679500848d4518458-3"
      ],
      "settings": {
        "color_scheme": "te-default",
        "padding_top": 40,
        "padding_bottom": 52
      }
    },
    "beb6aa28-dd50-4950-a521-305b23113ca0": {
      "type": "te-double-column",
      "blocks": {
        "4fae37ba-7c07-408a-b0c3-1001bc8d085a": {
          "type": "column__bullet",
          "settings": {
            "bullet__hide-icon-1": true,
            "bullet__icon-1": "option_a",
            "bullet__title-1": "Child powered",
            "bullet__message-1": "Phasellus non maximus risus. Praesent sem ante, aliquam quis elit et, laoreet eleifend lorem. Donec vitae erat lacinia mi laoreet fringilla.",
            "bullet__hide-icon-2": true,
            "bullet__icon-2": "option_a",
            "bullet__title-2": "",
            "bullet__message-2": "Phasellus non maximus risus. Praesent sem ante, aliquam quis elit et, laoreet eleifend lorem. Donec vitae erat lacinia mi laoreet fringilla.",
            "bullet__hide-icon-3": true,
            "bullet__icon-3": "option_a",
            "bullet__title-3": "",
            "bullet__message-3": ""
          }
        },
        "d808ccb3-9474-494d-8cc6-d81a7ae37733": {
          "type": "column__image",
          "settings": {
          }
        }
      },
      "block_order": [
        "4fae37ba-7c07-408a-b0c3-1001bc8d085a",
        "d808ccb3-9474-494d-8cc6-d81a7ae37733"
      ],
      "settings": {
        "color_scheme": "te-default",
        "padding_top": 40,
        "padding_bottom": 52,
        "subtitle": "Our Story",
        "title": "Etiam egestas in nec sed et",
        "caption": "In tincidunt pharetra consectetur sed duis facilisis metus. Etiam egestas in."
      }
    },
    "c57b265f-5637-40f4-a136-1dcecefc8170": {
      "type": "te-double-column",
      "blocks": {
        "76d23eff-d673-483e-88a6-5ecb90eee722": {
          "type": "column__image",
          "settings": {
          }
        },
        "1261e131-6fa1-4804-b794-8cc57a81bd97": {
          "type": "column__bullet",
          "settings": {
            "bullet__hide-icon-1": true,
            "bullet__icon-1": "option_a",
            "bullet__title-1": "Beautifully natural",
            "bullet__message-1": "Phasellus non maximus risus. Praesent sem ante, aliquam quis elit et, laoreet eleifend lorem. Donec vitae erat lacinia mi laoreet fringilla.",
            "bullet__hide-icon-2": false,
            "bullet__icon-2": "option_a",
            "bullet__title-2": "",
            "bullet__message-2": "",
            "bullet__hide-icon-3": true,
            "bullet__icon-3": "option_a",
            "bullet__title-3": "",
            "bullet__message-3": ""
          }
        }
      },
      "block_order": [
        "76d23eff-d673-483e-88a6-5ecb90eee722",
        "1261e131-6fa1-4804-b794-8cc57a81bd97"
      ],
      "settings": {
        "color_scheme": "te-default",
        "padding_top": 36,
        "padding_bottom": 52,
        "subtitle": "",
        "title": "",
        "caption": ""
      }
    },
    "51a288a0-33ac-4605-b840-cb2cc311a3d6": {
      "type": "te-double-column",
      "blocks": {
        "46bbc2ca-6e91-4092-b655-6661bff90035": {
          "type": "column__title",
          "settings": {
            "title__subtitle": "Choose conscious",
            "title__title": "Save your sanity and the planet",
            "title__message": "In ipsum nibh, fermentum a tempor ut, interdum eu ipsum. Integer volutpat suscipit neque, ut ullamcorper dolor aliquam non.",
            "title__hide-icon": false,
            "title__icon": "option_a"
          }
        },
        "19ea59d2-4cc5-4088-93e1-6c99a3f5e094": {
          "type": "column__bullet",
          "settings": {
            "bullet__hide-icon-1": true,
            "bullet__icon-1": "option_a",
            "bullet__title-1": "Fun and functional",
            "bullet__message-1": "Phasellus non maximus risus. Praesent sem ante, aliquam quis elit et, laoreet eleifend lorem. Donec vitae erat lacinia mi laoreet fringilla.",
            "bullet__hide-icon-2": true,
            "bullet__icon-2": "option_a",
            "bullet__title-2": "",
            "bullet__message-2": "",
            "bullet__hide-icon-3": true,
            "bullet__icon-3": "option_a",
            "bullet__title-3": "",
            "bullet__message-3": ""
          }
        }
      },
      "block_order": [
        "46bbc2ca-6e91-4092-b655-6661bff90035",
        "19ea59d2-4cc5-4088-93e1-6c99a3f5e094"
      ],
      "settings": {
        "color_scheme": "te-default",
        "padding_top": 40,
        "padding_bottom": 52,
        "subtitle": "",
        "title": "",
        "caption": ""
      }
    }
  },
  "order": [
    "main",
    "40304770-665c-4079-ab03-58ad2ee6edae",
    "beb6aa28-dd50-4950-a521-305b23113ca0",
    "c57b265f-5637-40f4-a136-1dcecefc8170",
    "51a288a0-33ac-4605-b840-cb2cc311a3d6"
  ]
}
